{
  "title": "Floodsafe",
  "onBoarding": {
    "additionalInfo": "Inyandiko zinyongera zisobanura hano, iyi ni umwanya.",
    "receiveFloodWarnings": "Akira imiburo y'umwuzure",
    "secondOnboardingPoint": "Indi ngingo",
    "thirdOnboardingPoint": "Kandi ikintu cyiza cya nyuma",
    "createAccount": "Kora konti",
    "logIn": "Injira",
    "nextStep": "Intambwe ikurikira"
  },
  "languageSelection": {
    "confirm": "Emeza",
    "chooseLanguage": "Hitamo ururimi"
  },
  "notifications": {
    "sendNotification": "Kohereza imenyesha"
  }
}
